[
    {
        "dialogue": "Sure.. big plastics are bad by themselves.. But you know what's worse?"
    },
    {
        "dialogue": "Microplastics.."
    },
    {
        "dialogue": "Microplastics are pieces of plastic that are less than 5 millimeters in length."
    },
    {
        "dialogue": "They can be dropped into the ocean by themselves, like microbeads, or they can shed off of other plastics."
    },
    {
        "dialogue": "Sunlight, waves or other wear and tear can deteriorate bigger plastics and create microplastics."
    },
    {
        "dialogue": "Since they're so small, lots of creatures ingest these microplastics."
    },
    {
        "dialogue": "Not good!"
    }
]